timcol/__init__.py
timcol/__main__.py
timcol/logfile/__init__.py
timcol/logfile/directive.py
timcol/logfile/entry.py
timcol/logfile/logfile.py
timcol/tool/__init__.py
timcol/tool/args.py
timcol/tool/editor.py
timcol/tool/main.py
timcol/tool/mutators.py
timcol/tool/upload.py
timcol/tool/view_renderer.py
timcol/tool/views/__init__.py
timcol/tool/views/_shared.py
timcol/tool/views/csv.py
timcol/tool/views/html.py
timcol/tool/views/invoice_template.htm.mustache
timcol/tool/views/register.py
timcol-0.2.0.dist-info/METADATA
timcol-0.2.0.dist-info/WHEEL
timcol-0.2.0.dist-info/entry_points.txt
timcol-0.2.0.dist-info/licenses/LICENSE
timcol-0.2.0.dist-info/RECORD
