Metadata-Version: 2.3
Name: timcol
Version: 0.2.0
Summary: Time tracking on the command line.
Author-email: itsjohncs <johnsullivan.pem@gmail.com>
License-File: LICENSE
Requires-Python: >=3.8
Requires-Dist: dateparser>=1.2.0
Requires-Dist: pystache>=0.6.5
Requires-Dist: tabulate>=0.9.0
